tests/__init__.py
tests/conftest.py
tests/test_csp_darknet53.py
tests/test_model.py
tests/test_yolov3_head.py
tests/test_yolov4_neck.py
tests/tools/__init__.py
tests/tools/test_convert_darknet_weights.py
tf2_yolov4/__init__.py
tf2_yolov4/anchors.py
tf2_yolov4/layers.py
tf2_yolov4/model.py
tf2_yolov4/backbones/__init__.py
tf2_yolov4/backbones/csp_darknet53.py
tf2_yolov4/heads/__init__.py
tf2_yolov4/heads/yolov3_head.py
tf2_yolov4/necks/__init__.py
tf2_yolov4/necks/yolov4_neck.py
tf2_yolov4/tools/__init__.py
tf2_yolov4/tools/convert_darknet_weights.py
tf2_yolov4-0.1.0.dist-info/LICENSE
tf2_yolov4-0.1.0.dist-info/METADATA
tf2_yolov4-0.1.0.dist-info/WHEEL
tf2_yolov4-0.1.0.dist-info/entry_points.txt
tf2_yolov4-0.1.0.dist-info/top_level.txt
tf2_yolov4-0.1.0.dist-info/RECORD
